Vpro/__init__.py
Vpro-0.296.dist-info/METADATA
Vpro-0.296.dist-info/WHEEL
Vpro-0.296.dist-info/top_level.txt
Vpro-0.296.dist-info/RECORD
