Metadata-Version: 2.1
Name: Vpro
Version: 0.296
Summary: This is a Machine Learning Module that grants one access to a Multilayer percepton with an adjustable number of hidden layers and neurons per each layer. It also includes functionality to train the network based on a database, and has adjustable innitialisation types, activation functions, and learning hyperparamters.
Author: Agastyaa Vishvanath
Requires-Dist: numpy
Requires-Dist: tqdm
